bio2bel_chebi/__init__.py
bio2bel_chebi/__main__.py
bio2bel_chebi/cli.py
bio2bel_chebi/constants.py
bio2bel_chebi/enrich.py
bio2bel_chebi/manager.py
bio2bel_chebi/models.py
bio2bel_chebi/run.py
bio2bel_chebi/utils.py
bio2bel_chebi/web.py
bio2bel_chebi/parser/__init__.py
bio2bel_chebi/parser/accession.py
bio2bel_chebi/parser/compounds.py
bio2bel_chebi/parser/inchis.py
bio2bel_chebi/parser/names.py
bio2bel_chebi/parser/relation.py
bio2bel_chebi-0.2.0.dist-info/LICENSE
bio2bel_chebi-0.2.0.dist-info/METADATA
bio2bel_chebi-0.2.0.dist-info/WHEEL
bio2bel_chebi-0.2.0.dist-info/entry_points.txt
bio2bel_chebi-0.2.0.dist-info/top_level.txt
bio2bel_chebi-0.2.0.dist-info/RECORD
