Metadata-Version: 2.1
Name: bio2bel-chebi
Version: 0.2.0
Summary: A package for converting ChEBI to BEL
Home-page: https://github.com/bio2bel/chebi
Author: Charles Tapley Hoyt
Author-email: charles.hoyt@scai.fraunhofer.de
Maintainer: Charles Tapley Hoyt
Maintainer-email: charles.hoyt@scai.fraunhofer.de
License: MIT License
Keywords: Biological Expression Language,BEL,ChEBI,Systems Biology,Networks Biology
Platform: UNKNOWN
Classifier: Development Status :: 4 - Beta
Classifier: Environment :: Console
Classifier: Intended Audience :: Developers
Classifier: Intended Audience :: Science/Research
Classifier: Operating System :: OS Independent
Classifier: Programming Language :: Python
Classifier: Programming Language :: Python :: 3 :: Only
Classifier: Programming Language :: Python :: 3.6
Classifier: Programming Language :: Python :: 3.7
Classifier: Topic :: Scientific/Engineering :: Bio-Informatics
Classifier: License :: OSI Approved :: MIT License
Requires-Dist: click
Requires-Dist: pandas
Requires-Dist: sqlalchemy
Requires-Dist: tqdm
Requires-Dist: bio2bel (<0.3.0,>=0.2.0)
Requires-Dist: pybel (<0.13.0,>=0.12.0)
Provides-Extra: docs
Requires-Dist: sphinx; extra == 'docs'
Requires-Dist: sphinx-rtd-theme; extra == 'docs'
Requires-Dist: sphinx-click; extra == 'docs'
Requires-Dist: sphinx-autodoc-typehints; extra == 'docs'
Provides-Extra: web
Requires-Dist: flask; extra == 'web'
Requires-Dist: flask-admin; extra == 'web'
